vncuda/CTPMarket.py
vncuda/CTPMarketType.py
vncuda/__init__.py
vncuda/globalType.py
vncuda/globalvar.py
vncuda/main.py
vncuda-1.0.dist-info/LICENSE
vncuda-1.0.dist-info/METADATA
vncuda-1.0.dist-info/WHEEL
vncuda-1.0.dist-info/top_level.txt
vncuda-1.0.dist-info/RECORD
