Metadata-Version: 2.1
Name: vncuda
Version: 1.0
Summary: Quantitative software
Home-page: http://www.vnpy.cn
Author: 上海量贝信息科技有限公司
Author-email: public@vnpy.cn
License: GPLV3
Platform: UNKNOWN
Requires-Python: >=3.5
License-File: LICENSE
Requires-Dist: configparser
